{
    "key": "group_555ce0c869200",
    "title": "Post Content",
    "fields": [
        {
            "key": "field_555ce0b8dcb16",
            "label": "Content Blocks",
            "name": "content_blocks",
            "prefix": "",
            "type": "flexible_content",
            "instructions": "A structured way to write your posts.",
            "required": 0,
            "conditional_logic": 0,
            "wrapper": {
                "width": "",
                "class": "",
                "id": ""
            },
            "button_label": "Add Content",
            "min": "",
            "max": "",
            "layouts": [
                {
                    "key": "5443e2961805c",
                    "name": "text_block",
                    "label": "Text",
                    "display": "row",
                    "sub_fields": [
                        {
                            "key": "field_555ce0b8dcb17",
                            "label": "Text",
                            "name": "section_text",
                            "prefix": "",
                            "type": "textarea",
                            "instructions": "Plain paragraph text. No headlines. This will display in two columns at desktop view.",
                            "required": 0,
                            "conditional_logic": 0,
                            "wrapper": {
                                "width": "",
                                "class": "",
                                "id": ""
                            },
                            "default_value": "",
                            "placeholder": "",
                            "maxlength": "",
                            "rows": "",
                            "new_lines": "wpautop",
                            "readonly": 0,
                            "disabled": 0
                        }
                    ],
                    "min": "",
                    "max": ""
                },
                {
                    "key": "5437f2c02fedf",
                    "name": "text_image_block",
                    "label": "Text and Image Block",
                    "display": "row",
                    "sub_fields": [
                        {
                            "key": "field_555ce0b8dcb18",
                            "label": "Image",
                            "name": "image",
                            "prefix": "",
                            "type": "image",
                            "instructions": "This image will display to the left of the text.",
                            "required": 0,
                            "conditional_logic": 0,
                            "wrapper": {
                                "width": "",
                                "class": "",
                                "id": ""
                            },
                            "return_format": "url",
                            "preview_size": "thumbnail",
                            "library": "all",
                            "min_width": "",
                            "min_height": "",
                            "min_size": "",
                            "max_width": "",
                            "max_height": "",
                            "max_size": "",
                            "mime_types": ""
                        },
                        {
                            "key": "field_555ce0b8dcb19",
                            "label": "Text",
                            "name": "text",
                            "prefix": "",
                            "type": "textarea",
                            "instructions": "This will be descriptive text to the right of the image.",
                            "required": 0,
                            "conditional_logic": 0,
                            "wrapper": {
                                "width": "",
                                "class": "",
                                "id": ""
                            },
                            "default_value": "",
                            "placeholder": "",
                            "maxlength": "",
                            "rows": "",
                            "new_lines": "",
                            "readonly": 0,
                            "disabled": 0
                        },
                        {
                            "key": "field_555ce0b8dcb1a",
                            "label": "Image Location",
                            "name": "image_location",
                            "prefix": "",
                            "type": "radio",
                            "instructions": "Should the image be shown on the right or left?",
                            "required": 0,
                            "conditional_logic": 0,
                            "wrapper": {
                                "width": "",
                                "class": "",
                                "id": ""
                            },
                            "choices": {
                                "Right": "Right",
                                "Left": "Left"
                            },
                            "other_choice": 0,
                            "save_other_choice": 0,
                            "default_value": "",
                            "layout": "horizontal"
                        }
                    ],
                    "min": "",
                    "max": ""
                },
                {
                    "key": "5437f1f4676b0",
                    "name": "large_image_block",
                    "label": "Large Image Block",
                    "display": "row",
                    "sub_fields": [
                        {
                            "key": "field_555ce0b8dcb1b",
                            "label": "Image",
                            "name": "image",
                            "prefix": "",
                            "type": "image",
                            "instructions": "Recommended dimensions are 1040x600. Images should not be more than 1040px wide.",
                            "required": 0,
                            "conditional_logic": 0,
                            "wrapper": {
                                "width": "",
                                "class": "",
                                "id": ""
                            },
                            "return_format": "url",
                            "preview_size": "thumbnail",
                            "library": "all",
                            "min_width": "",
                            "min_height": "",
                            "min_size": "",
                            "max_width": "",
                            "max_height": "",
                            "max_size": "",
                            "mime_types": ""
                        },
                        {
                            "key": "field_555ce0b8dcb1c",
                            "label": "Caption",
                            "name": "caption",
                            "prefix": "",
                            "type": "text",
                            "instructions": "This will be a small line under the image. You can leave it blank.",
                            "required": 0,
                            "conditional_logic": 0,
                            "wrapper": {
                                "width": "",
                                "class": "",
                                "id": ""
                            },
                            "default_value": "",
                            "placeholder": "",
                            "prepend": "",
                            "append": "",
                            "maxlength": "",
                            "readonly": 0,
                            "disabled": 0
                        }
                    ],
                    "min": "",
                    "max": ""
                },
                {
                    "key": "5437f4bfd8415",
                    "name": "blank",
                    "label": "Blank",
                    "display": "row",
                    "sub_fields": [
                        {
                            "key": "field_555ce0b8dcb1d",
                            "label": "Blank",
                            "name": "wysiwyg",
                            "prefix": "",
                            "type": "wysiwyg",
                            "instructions": "You can add whatever content you like here, but keep it simple - this is mainly a spot for shortcodes.",
                            "required": 0,
                            "conditional_logic": 0,
                            "wrapper": {
                                "width": "",
                                "class": "",
                                "id": ""
                            },
                            "default_value": "",
                            "tabs": "all",
                            "toolbar": "full",
                            "media_upload": 1
                        }
                    ],
                    "min": "",
                    "max": ""
                }
            ]
        }
    ],
    "location": [
        [
            {
                "param": "post_type",
                "operator": "==",
                "value": "post"
            }
        ]
    ],
    "menu_order": 0,
    "position": "normal",
    "style": "seamless",
    "label_placement": "top",
    "instruction_placement": "label",
    "hide_on_screen": [
        "the_content",
        "custom_fields",
        "revisions",
        "format",
        "page_attributes"
    ],
    "modified": 1432150497
}