{
    "key": "group_54695d78426ae",
    "title": "Content Blocks",
    "fields": [
        {
            "key": "field_5437f1ee2fedd",
            "label": "Content Blocks",
            "name": "content_blocks",
            "prefix": "",
            "type": "flexible_content",
            "instructions": "Note: if this is the \"Meisters\" or \"Deals\" page, this content will show below the Deal\/Meister posts.",
            "required": 0,
            "conditional_logic": 0,
            "wrapper": {
                "width": "",
                "class": "",
                "id": ""
            },
            "button_label": "Add Content",
            "min": "",
            "max": "",
            "layouts": [
                {
                    "key": "5443e2961805c",
                    "name": "text_block",
                    "label": "Text",
                    "display": "row",
                    "sub_fields": [
                        {
                            "key": "field_54593fc3d8b9f",
                            "label": "Text",
                            "name": "section_text",
                            "prefix": "",
                            "type": "wysiwyg",
                            "instructions": "Plain paragraph text. No headlines. This will display in two columns at desktop view.",
                            "required": 0,
                            "conditional_logic": 0,
                            "wrapper": {
                                "width": "",
                                "class": "",
                                "id": ""
                            },
                            "default_value": "",
                            "tabs": "all",
                            "toolbar": "text_based",
                            "media_upload": 1
                        },
                        {
                            "key": "field_546962b3ad161",
                            "label": "Heading",
                            "name": "heading",
                            "prefix": "",
                            "type": "text",
                            "instructions": "Leave blank if only paragraph text.",
                            "required": 0,
                            "conditional_logic": 0,
                            "wrapper": {
                                "width": "",
                                "class": "",
                                "id": ""
                            },
                            "default_value": "",
                            "placeholder": "",
                            "prepend": "",
                            "append": "",
                            "maxlength": "",
                            "readonly": 0,
                            "disabled": 0
                        }
                    ],
                    "min": "",
                    "max": ""
                },
                {
                    "key": "5437f2c02fedf",
                    "name": "text_image_block",
                    "label": "Text and Image Block",
                    "display": "row",
                    "sub_fields": [
                        {
                            "key": "field_5437f2d22fee0",
                            "label": "Image",
                            "name": "image",
                            "prefix": "",
                            "type": "image",
                            "instructions": "This image will be on the left!",
                            "required": 0,
                            "conditional_logic": 0,
                            "wrapper": {
                                "width": "",
                                "class": "",
                                "id": ""
                            },
                            "return_format": "url",
                            "preview_size": "thumbnail",
                            "library": "all",
                            "min_width": 0,
                            "min_height": 0,
                            "min_size": 0,
                            "max_width": 0,
                            "max_height": 0,
                            "max_size": 0,
                            "mime_types": ""
                        },
                        {
                            "key": "field_5437f3102fee1",
                            "label": "Text",
                            "name": "text",
                            "prefix": "",
                            "type": "wysiwyg",
                            "instructions": "This will be descriptive text to the right of the image.",
                            "required": 0,
                            "conditional_logic": 0,
                            "wrapper": {
                                "width": "",
                                "class": "",
                                "id": ""
                            },
                            "default_value": "",
                            "tabs": "all",
                            "toolbar": "text_based",
                            "media_upload": 1
                        },
                        {
                            "key": "field_5443e7631d17b",
                            "label": "Image Location",
                            "name": "image_location",
                            "prefix": "",
                            "type": "radio",
                            "instructions": "Should the image be shown on the right or left?",
                            "required": 0,
                            "conditional_logic": 0,
                            "wrapper": {
                                "width": "",
                                "class": "",
                                "id": ""
                            },
                            "choices": {
                                "Right": "Right",
                                "Left": "Left"
                            },
                            "other_choice": 0,
                            "save_other_choice": 0,
                            "default_value": "",
                            "layout": "horizontal"
                        },
                        {
                            "key": "field_5469627959403",
                            "label": "Heading",
                            "name": "heading",
                            "prefix": "",
                            "type": "text",
                            "instructions": "Leave blank if you only want paragraph text.",
                            "required": 0,
                            "conditional_logic": 0,
                            "wrapper": {
                                "width": "",
                                "class": "",
                                "id": ""
                            },
                            "default_value": "",
                            "placeholder": "",
                            "prepend": "",
                            "append": "",
                            "maxlength": "",
                            "readonly": 0,
                            "disabled": 0
                        }
                    ],
                    "min": "",
                    "max": ""
                },
                {
                    "key": "54b5241db0eef",
                    "name": "shortcode",
                    "label": "Shortcode",
                    "display": "row",
                    "sub_fields": [
                        {
                            "key": "field_54b52422b0ef0",
                            "label": "Shortcode",
                            "name": "shortcode",
                            "prefix": "",
                            "type": "wysiwyg",
                            "instructions": "Type any shortcodes here.",
                            "required": 0,
                            "conditional_logic": 0,
                            "wrapper": {
                                "width": "",
                                "class": "",
                                "id": ""
                            },
                            "default_value": "",
                            "tabs": "text",
                            "toolbar": "full",
                            "media_upload": 1
                        }
                    ],
                    "min": "",
                    "max": ""
                },
                {
                    "key": "5437f4bfd8415",
                    "name": "blank",
                    "label": "HTML",
                    "display": "row",
                    "sub_fields": [
                        {
                            "key": "field_5437f4ccd8416",
                            "label": "Blank",
                            "name": "wysiwyg",
                            "prefix": "",
                            "type": "textarea",
                            "instructions": "Type any HTML here.",
                            "required": 0,
                            "conditional_logic": 0,
                            "wrapper": {
                                "width": "",
                                "class": "",
                                "id": ""
                            },
                            "default_value": "",
                            "placeholder": "",
                            "maxlength": "",
                            "rows": "",
                            "new_lines": "",
                            "readonly": 0,
                            "disabled": 0
                        }
                    ],
                    "min": "",
                    "max": ""
                }
            ]
        }
    ],
    "location": [
        [
            {
                "param": "post_type",
                "operator": "==",
                "value": "page"
            }
        ]
    ],
    "menu_order": 0,
    "position": "normal",
    "style": "seamless",
    "label_placement": "top",
    "instruction_placement": "label",
    "hide_on_screen": [
        "the_content",
        "excerpt",
        "custom_fields",
        "discussion",
        "comments",
        "revisions",
        "author",
        "format",
        "page_attributes",
        "featured_image",
        "categories",
        "tags",
        "send-trackbacks"
    ],
    "modified": 1426696160,
    "local": "json"
}